engine/__init__.py
engine/agents/__init__.py
engine/agents/agent.py
engine/agents/code_analyzer.py
engine/agents/optimizer.py
engine/agents/results.py
engine/agents/reviewer.py
engine/cli/__init__.py
engine/cli/cli.py
engine/functionality_mapper/__init__.py
engine/functionality_mapper/base_mapper.py
engine/modernizers/__init__.py
engine/modernizers/cobol_system/__init__.py
engine/modernizers/cobol_system/modernizer.yaml
engine/modernizers/cobol_system/functionality_mapper/__init__.py
engine/modernizers/cobol_system/functionality_mapper/functionality_mapper.py
engine/modernizers/cobol_system/generators/python_generator.py
engine/modernizers/cobol_system/generators/template_generator.py
engine/modernizers/cobol_system/ir/cobol_to_ir.py
engine/modernizers/cobol_system/ir/ir.py
engine/modernizers/cobol_system/parsers/__init__.py
engine/modernizers/cobol_system/parsers/cobol_lst.py
engine/modernizers/cobol_system/parsers/cobol85/Cobol85.g4
engine/modernizers/cobol_system/parsers/cobol85/Cobol85.interp
engine/modernizers/cobol_system/parsers/cobol85/Cobol85.tokens
engine/modernizers/cobol_system/parsers/cobol85/Cobol85Lexer.interp
engine/modernizers/cobol_system/parsers/cobol85/Cobol85Lexer.py
engine/modernizers/cobol_system/parsers/cobol85/Cobol85Lexer.tokens
engine/modernizers/cobol_system/parsers/cobol85/Cobol85Listener.py
engine/modernizers/cobol_system/parsers/cobol85/Cobol85Parser.py
engine/modernizers/cobol_system/parsers/cobol85/Cobol85Preprocessor.g4
engine/modernizers/cobol_system/parsers/cobol85/Cobol85Preprocessor.interp
engine/modernizers/cobol_system/parsers/cobol85/Cobol85Preprocessor.tokens
engine/modernizers/cobol_system/parsers/cobol85/Cobol85PreprocessorLexer.interp
engine/modernizers/cobol_system/parsers/cobol85/Cobol85PreprocessorLexer.py
engine/modernizers/cobol_system/parsers/cobol85/Cobol85PreprocessorLexer.tokens
engine/modernizers/cobol_system/parsers/cobol85/Cobol85PreprocessorListener.py
legacy2modern-0.1.0.dist-info/licenses/LICENSE
legacy2modern-0.1.0.dist-info/METADATA
legacy2modern-0.1.0.dist-info/WHEEL
legacy2modern-0.1.0.dist-info/entry_points.txt
legacy2modern-0.1.0.dist-info/top_level.txt
legacy2modern-0.1.0.dist-info/RECORD
