Metadata-Version: 2.4
Name: legacy2modern
Version: 0.1.0
Summary: AI-Powered Legacy Code Transpilation Engine with Modern CLI
Home-page: https://github.com/astrio-ai/legacy2modern
Author: Naing Oo Lwin
Author-email: Naing Oo Lwin <naingoolwin.astrio@gmail.com>
Maintainer-email: Naing Oo Lwin <naingoolwin.astrio@gmail.com>
License: Apache-2.0
Project-URL: Homepage, https://github.com/astrio-ai/legacy2modern
Project-URL: Documentation, https://github.com/astrio-ai/legacy2modern#readme
Project-URL: Repository, https://github.com/astrio-ai/legacy2modern
Project-URL: Bug Tracker, https://github.com/astrio-ai/legacy2modern/issues
Keywords: cobol,transpiler,legacy,modernization,python,cli
Classifier: Development Status :: 3 - Alpha
Classifier: Intended Audience :: Developers
Classifier: License :: OSI Approved :: Apache Software License
Classifier: Operating System :: OS Independent
Classifier: Programming Language :: Python :: 3
Classifier: Programming Language :: Python :: 3.10
Classifier: Programming Language :: Python :: 3.11
Classifier: Programming Language :: Python :: 3.12
Classifier: Topic :: Software Development :: Code Generators
Classifier: Topic :: Software Development :: Compilers
Classifier: Topic :: Software Development :: Libraries :: Python Modules
Requires-Python: >=3.10
License-File: LICENSE
Requires-Dist: pytest>=8.0.0
Requires-Dist: python-dotenv>=1.0.0
Requires-Dist: click>=8.1.0
Requires-Dist: rich>=13.0.0
Requires-Dist: typer>=0.9.0
Requires-Dist: prompt_toolkit>=3.0.0
Requires-Dist: pygments>=2.15.0
Requires-Dist: openai>=1.0.0
Requires-Dist: anthropic>=0.7.0
Requires-Dist: requests>=2.31.0
Requires-Dist: beautifulsoup4>=4.12.0
Requires-Dist: lxml>=4.9.0
Requires-Dist: antlr4-python3-runtime>=4.9.0
Requires-Dist: jinja2>=3.0.0
Requires-Dist: colorlog>=6.0.0
Provides-Extra: dev
Requires-Dist: pytest>=8.0.0; extra == "dev"
Requires-Dist: pytest-cov>=4.0.0; extra == "dev"
Requires-Dist: black>=23.0.0; extra == "dev"
Requires-Dist: flake8>=6.0.0; extra == "dev"
Requires-Dist: mypy>=1.0.0; extra == "dev"
Dynamic: author
Dynamic: home-page
Dynamic: license-file
Dynamic: requires-python
